DroneBlocksTelloSimulator/DroneBlocksSimulatorContextManager.py
DroneBlocksTelloSimulator/__init__.py
DroneBlocksTelloSimulator/drone.py
DroneBlocksTelloSimulator/enforce_types.py
DroneBlocksTelloSimulator/swarm.py
DroneBlocksTelloSimulator/tello.py
DroneBlocksTelloSimulator-0.0.8.dist-info/LICENSE
DroneBlocksTelloSimulator-0.0.8.dist-info/METADATA
DroneBlocksTelloSimulator-0.0.8.dist-info/WHEEL
DroneBlocksTelloSimulator-0.0.8.dist-info/top_level.txt
DroneBlocksTelloSimulator-0.0.8.dist-info/RECORD
