Metadata-Version: 2.1
Name: DroneBlocksTelloSimulator
Version: 0.0.8
Summary: Program a drone with the DroneBlocks Simulator and then deploy to Tello
Home-page: https://github.com/dbaldwin/DroneBlocks-Python-Simulator
Author: Dennis Baldwin
Author-email: db@droneblocks.io
Project-URL: Bug Tracker, https://github.com/dbaldwin/DroneBlocks-Python-Simulator/issues
Classifier: Programming Language :: Python :: 3
Classifier: License :: OSI Approved :: MIT License
Classifier: Operating System :: OS Independent
Requires-Python: >=3.6
License-File: LICENSE
Requires-Dist: paho-mqtt >=1.6.1
